boost_spider/__init__.py
boost_spider/http/__init__.py
boost_spider/http/request_client.py
boost_spider/http/user_agent.py
boost_spider/sink/__init__.py
boost_spider/sink/dataset_sink.py
boost_spider/sink/excel_sink.py
boost_spider/sink/json_sink.py
boost_spider/sink/momgo_sink.py
boost_spider/sink/mysql_sink.py
boost_spider/sink/sink_helper.py
boost_spider/sink/sqlite_sink.py
boost_spider/utils/__init__.py
boost_spider/utils/thread_local_obj.py
boost_spider-1.5.dist-info/METADATA
boost_spider-1.5.dist-info/WHEEL
boost_spider-1.5.dist-info/top_level.txt
boost_spider-1.5.dist-info/RECORD
