Metadata-Version: 2.4
Name: boost_spider
Version: 1.5
Summary: 横冲直闯 自由奔放 无回调 无继承写法的高速爬虫框架
Home-page: https://github.com/ydf0509/boost_spider
Author: bfzs
Author-email: ydf0509@sohu.com
Maintainer: ydf
Maintainer-email: ydf0509@sohu.com
License: BSD License
Keywords: scrapy,funboost,distributed-framework,function-scheduling,rabbitmq,rocketmq,kafka,nsq,redis,sqlachemy,consume-confirm,timing,task-scheduling,apscheduler,pulsar,mqtt,kombu,的,celery,框架,分布式调度
Platform: all
Classifier: Development Status :: 4 - Beta
Classifier: Operating System :: OS Independent
Classifier: Intended Audience :: Developers
Classifier: License :: OSI Approved :: BSD License
Classifier: Programming Language :: Python
Classifier: Programming Language :: Python :: Implementation
Classifier: Programming Language :: Python :: 3.6
Classifier: Programming Language :: Python :: 3.7
Classifier: Programming Language :: Python :: 3.8
Classifier: Programming Language :: Python :: 3.9
Classifier: Programming Language :: Python :: 3.10
Classifier: Programming Language :: Python :: 3.11
Classifier: Topic :: Software Development :: Libraries
Requires-Dist: funboost
Requires-Dist: universal_object_pool
Requires-Dist: pymysql
Requires-Dist: pymongo
Requires-Dist: parsel
Requires-Dist: requests
Dynamic: author
Dynamic: author-email
Dynamic: classifier
Dynamic: description
Dynamic: description-content-type
Dynamic: home-page
Dynamic: keywords
Dynamic: license
Dynamic: maintainer
Dynamic: maintainer-email
Dynamic: platform
Dynamic: requires-dist
Dynamic: summary
